aslib/__init__.py
aslib/amqp.py
aslib/configs.py
aslib/db.py
aslib/logs.py
aslib/options.py
aslib/paths.py
aslib/progs.py
aslib/signals.py
aslib/times.py
aslib/utils.py
aslib/version.py
aslib-1.0.3.dist-info/METADATA
aslib-1.0.3.dist-info/WHEEL
aslib-1.0.3.dist-info/entry_points.txt
aslib-1.0.3.dist-info/top_level.txt
aslib-1.0.3.dist-info/RECORD
