Metadata-Version: 2.1
Name: aslib
Version: 1.0.3
Summary: UNKNOWN
Home-page: http://www.faker.aslib.com
Author: aslib
Author-email: aslib@demo.com
License: UNKNOWN
Platform: UNKNOWN
Classifier: Programming Language :: Python :: 3
Classifier: License :: OSI Approved :: MIT License
Classifier: Operating System :: OS Independent
Requires-Python: >=3.7,<4
Requires-Dist: loguru (==0.6.0)
Requires-Dist: pika (==1.2.1)
Requires-Dist: PyYAML (==6.0)
Requires-Dist: SQLAlchemy (==1.4.37)
Requires-Dist: PyMySQL (==1.0.2)
Requires-Dist: requests (==2.28.0)
Requires-Dist: protobuf (==3.19.4)
Requires-Dist: psutil (==5.9.0)
